{"last_check_time":1593725535,"next_check_time":1593725835,"last_check_human_time":"2020-07-02 21:32:15","video":{"publishedAt":"2020-06-27T23:16:10Z","channelId":"UCmxNofANlC5f8CFBwaJ74hA","videoId":"FfIoILh4LBc","title":"Saint Peter&#39;s First Miracle PART 2\u2014Pre-K &amp; Kindergarten Sunday School Lesson","description":"","images":{"default":{"url":"https:\/\/i.ytimg.com\/vi\/FfIoILh4LBc\/default.jpg","width":120,"height":90},"medium":{"url":"https:\/\/i.ytimg.com\/vi\/FfIoILh4LBc\/mqdefault.jpg","width":320,"height":180},"high":{"url":"https:\/\/i.ytimg.com\/vi\/FfIoILh4LBc\/hqdefault.jpg","width":480,"height":360}},"liveBroadCast":0},"next_check":"2020-07-02 21:37:15"}